Computational_Block/B_type.v
module B_type(
    input signed [31:0] rv1,
    input signed [31:0] rv2,
    input [2:0] func3,
    output reg result
);
    wire [31:0] tempA; // rv1
    wire [31:0] tempB; // rv2
    
    // Convert to unsigned
    assign tempA = rv1;
    assign tempB = rv2;

    always @(func3 or rv1 or rv2) begin
        case(func3)
            3'b000: result = (rv1 == rv2);
            3'b001: result = (rv1 != rv2);
            3'b100: result = (rv1 < rv2);
            3'b101: result = (rv1 >= rv2);
            3'b110: result = (tempA < tempB);
            3'b111: result = (tempA >= tempB);
        endcase
    end

endmodule

Computational_Block/S_type.v
module S_Type(
    input [2:0] func3,
    input [31:0] address,
    output reg [3:0] we_out
);

    always @(func3 or address) begin
        case(func3)
            3'b000: we_out = (4'b0001 << address[1:0]);
            3'b001: we_out = (4'b0011 << address[1:0]);
            3'b010: we_out = 4'b1111;
        endcase
    end

endmodule

Computational_Block/I2_type.v
module I2_Type(
    input [2:0] func3,
    input [31:0] address,
    input [31:0] drdata,
    output reg[31:0] out
);
    reg [31:0] offset;
    always@(func3 or address or drdata)
    begin   
        offset = (address[1:0]<<3);
        case(func3)
        3'b000: out = {{24{drdata[offset+7]}}, drdata[offset +: 8]};    //LB
        3'b001: out = {{16{drdata[offset+15]}}, drdata[offset +: 16]};  //LH
        3'b010: out = drdata;                                   			//LW
        3'b100: out = {24'b0, drdata[offset +: 8]};             			//LBU
        3'b101: out = {16'b0, drdata[offset +: 16]};            			//LHU
        endcase
    end

endmodule

Computational_Block/I_type.v
module I_Type(
    input srli_e,
    input signed [31:0] imm, 
    input signed [31:0] rdata1, 
    input [2:0] func3,
    output reg [31:0] out
);
    wire [31:0] tempA; // rdata1
    wire [11:0] tempB; // Immediate
    
    // Convert to unsigned
    assign tempA = rdata1;
    assign tempB = imm;

    always @(func3 or rdata1 or imm) begin
        case(func3)
            3'b000: out = rdata1 + imm ; //addi
            3'b001: out = rdata1 << imm[4:0]; // slli
            3'b010: out = rdata1 < imm; // slti
            3'b011: out = tempA < tempB; // sltiu
            3'b100: out = rdata1 ^ imm; // xori
            3'b101: 
                begin
                    if(srli_e)
                        out = rdata1 >> imm[4:0]; // srli 
                    else
                        out = rdata1 >>> imm[4:0]; // srai
                end
            3'b110: out = rdata1 | imm;
            3'b111: out = rdata1 & imm;

        endcase
    end

endmodule

Computational_Block/R_type.v
module R_Type(
    input [2:0] func3,
    input [6:0] func7,
    input signed [31:0] operator1,
    input signed [31:0] operator2,
    output reg[31:0] out
);
    wire [31:0] tempA;
    wire [31:0] tempB;
    assign tempA = operator1;
    assign tempB = operator2;

    always @(func3 or func7 or operator1 or operator2) 
    begin
    	case(func3)
            3'b000:   
                begin 
                    case(func7)
                        7'b0000000: out = operator1+operator2; // add
                        7'b0000001: out = operator1*operator2; // mul
                        7'b0100000: out = operator1-operator2; // sub
                    endcase
                end

            3'b001:    out = operator1<<operator2[4:0];	    // sll
            3'b010:    out = operator1<operator2;           // slt
            3'b011:    out = tempA<tempB;                     // sltu
            3'b100:
                begin 
                    case(func7)
                        7'b0000000: out = operator1^operator2;  // xor
                        7'b0000001: out = operator1/operator2; //  div
                    endcase
                end
                    
            3'b101:   
                begin
                    if(func7 != 7'b0100000)
                        out = operator1>>operator2[4:0];  // srl 
                    else
                       out = operator1>>>operator2[4:0]; // sra
                end

            3'b110:
                begin 
                    case(func7)
                        7'b0000000: out = operator1|operator2; // or
                        7'b0000001: out = operator1%operator2; // rem
                    endcase
                end
                    
            3'b111:    out = operator1&operator2;       //and
        endcase
    end

endmodule

Memory_Block/register_file.v
module register_file(
    input clk,

    // Instruction set input (Read)
    input [4:0] rs1, 
    input [4:0] rs2,
    input [4:0] rd,

    input [31:0] regdata,
    input wer,

    // Output (register values)
    output [31:0] rv1, 
    output [31:0] rv2
);
    reg [31:0] r[0:31]; // 32 Reg 32 bits

    integer i;
    initial begin
        for(i=0; i<=31; i = i+1)
            r[i]=0;
    end

    assign rv1 = r[rs1];
    assign rv2 = r[rs2];

    always @(posedge clk) 
    begin
        if(wer && rd!=0)
            r[rd] = regdata;
        $writememh("dump_registers.mem", r);
    end
endmodule

Memory_Block/data_mem.v
module data_mem(
    input clk,
    input [31:0] address, // Address
    input [31:0] dwdata, // Data Write
    input [3:0] we, // Write Enable
    output [31:0] drdata // Data Read
);
    reg [7:0] mem[0:1024];
    wire [31:0] byte0, byte1, byte2, byte3;

    initial $readmemh("data_memory.mem", mem);

    assign byte0 = (address & 32'hfffffffc)+ 32'h00000000;
    assign byte1 = (address & 32'hfffffffc)+ 32'h00000001;
    assign byte2 = (address & 32'hfffffffc)+ 32'h00000002;
    assign byte3 = (address & 32'hfffffffc)+ 32'h00000003;

    // Little Endian Reading
    assign drdata = {mem[byte3], mem[byte2], mem[byte1], mem[byte0]};

    // Little Endian Writing
    always @(posedge clk) begin
        if(we[0] == 1)
            mem[byte0] = dwdata[7:0];
        if(we[1] == 1)
            mem[byte1] = dwdata[15:8];
        if(we[2] == 1)
            mem[byte2] = dwdata[23:16];
        if(we[3] == 1)
            mem[byte3] = dwdata[31:24];
        
        $writememh("data_memory.mem", mem);
    end
endmodule

Memory_Block/instr_mem.v
module instr_mem(
    input [31:0] iaddr,
    output [31:0] idata
);
    reg [31:0] inst_arr[0:1024];
    initial begin
		$readmemh("instruction_memory.mem", inst_arr);
	 end
    assign idata = inst_arr[iaddr[31:2]];
endmodule

CtrlUnit.v
`include "Memory_Block/register_file.v"
`include "Memory_Block/instr_mem.v"
`include "Memory_Block/data_mem.v"

`include "Computational_Block/R_type.v"
`include "Computational_Block/I_type.v"
`include "Computational_Block/I2_type.v"
`include "Computational_Block/S_type.v"
`include "Computational_Block/B_type.v"

module CTRL_UNIT (
    input clk,
    input reset,

	output reg [31:0] PC,  // Stores current Program counter value
	output reg [31:0] nextPC,    // Stores the value that is to be assigned in the next clk cycle to Program counter
    output reg isDone
);
    // 
    reg [3:0] we; // Write enable signal for each byte of 32-b word.
	reg we_reg;   // Write enable for register file.
    reg [4:0] rd,rs1,rs2; // Input reg
    wire [31:0] instr32;   // data from instruction memory
    wire [31:0] rv1, rv2; // Register values
    reg [31:0] regdata; 

    // Data Memory 
    reg [31:0] daddr;  // Address to acess memory
    wire [31:0] drdata;  // Data readed from Memmory
    reg [31:0] dwdata; // Data to be written in memory

    // CPU Clock Signal
    always@(posedge clk)
    begin
        if(reset) 
            PC = 0; // Reset program counter PC
        else
            PC = nextPC; // Assign next cycle PC value to current PC
    end 

    //
    wire [31:0] R_type_result;
    reg [2:0] func3;
    reg [6:0] func7;

    wire [31:0] I_type_result;
    reg signed [31:0] imm;

    wire [3:0] we_S_result;

    wire [31:0] I2_type_result;

    // Instances
    instr_mem im1(PC, instr32);
    data_mem dm1(clk, daddr, dwdata, we, drdata);
    register_file reg1(clk, rs1, rs2, rd, regdata, we_reg, rv1, rv2);

    // 
    always @(*) begin
        case (instr32[6:0])
            7'b0000000:
                begin
                    isDone = 1;
                end

            7'b0000011: // TIPO I (Load operations)
                begin
                    func3 = instr32[14:12];
                    rd = instr32[11:7];
                    rs1 = instr32[19:15]; 
                    imm = {{20{instr32[31]}},instr32[31:20]};
                    we_reg = 1;
                    we = 4'b0;
                    daddr = rv1+imm;    
                    regdata = I2_type_result;
                    nextPC = PC+4;
                end 

            7'b0010011: // TIPO I (Immediate Operations)
                begin
                    imm = { {20{instr32[31]}}, instr32[31:20] }; // Convert to 32 bits, repeat 20 bits with sign if exists. This is for negative numbers
                    rs1 = instr32[19:15];
                    func3 = instr32[14:12];
                    rd = instr32[11:7];
                    we_reg = 1;
                    we = 4'b0;
                    regdata = I_type_result;
                    nextPC = PC+4;
                end

            7'b0010111: // TIPO U (add upper immediate to PC) 
                begin
					rd = instr32[11:7];
					imm = {instr32[31:12], 12'b0};
					we_reg = 1;
					we = 4'b0;
					regdata = PC + imm;
					nextPC = PC + 4;
				end

            7'b0100011: // TIPO S (Store)
                begin
                    imm = { {20{instr32[31]}}, instr32[31:25], instr32[11:7] };
                    rs1 = instr32[19:15];
                    rs2 = instr32[24:20];
                    func3 = instr32[14:12];
                    daddr = rv1 + imm;
                    
                    case(func3)
                        3'b000: dwdata = {rv2[7:0], rv2[7:0], rv2[7:0], rv2[7:0]};
                        3'b001: dwdata = {rv2[15:0], rv2[15:0]};
                        3'b010: dwdata = rv2[31:0];
                    endcase

                    we = we_S_result;
                    nextPC = PC+4;
                end

            7'b0110011: // TIPO R (Arithmetic Operations)
                begin
                    rd = instr32[11:7];
                    rs1 = instr32[19:15];
                    rs2 = instr32[24:20];
                    func3 = instr32[14:12];
                    func7 =  instr32[31:25];
                    we_reg = 1;
                    we = 4'b0;
                    regdata = R_type_result;
                    nextPC = PC+4; 
                end

            7'b0110111: // TIPO U (load upper immediate)
                begin
					rd = instr32[11:7];
					imm = {instr32[31:12], 12'b0};
					we_reg = 1;
					we = 4'b0;
					regdata = imm;
					nextPC = PC+4;
				end

            7'b1100011: // TIPO B (Branch if)
                begin
                    rs1 = instr32[19:15];
                    rs2 = instr32[24:20];
                    func3 = instr32[14:12];
                    imm = {{19{instr32[31]}}, instr32[31], instr32[7], instr32[30:25], instr32[11:8], 1'b0};
                    
                    we_reg = 0;
                    we = 4'b0;
                    
                    if(B_type_result)
                        nextPC = (PC + imm);
                    else
                        nextPC = (PC + 4);

                end

            7'b1100111: // TIPO I (jump and link register)
                begin
                    rs1 = instr32[19:15];
					rd = instr32[11:7];
					imm = {{20{instr32[31]}}, instr32[31:20]};
					we_reg = 1;
					we = 4'b0;
					regdata = PC + 4;
					nextPC = (rv1+imm) & 32'hfffffffe; 
                end

            7'b1101111: // TIPO J (jump and link)
                begin
                    rd = instr32[11:7];
					imm = {{11{instr32[31]}}, instr32[31], instr32[19:12], instr32[20], instr32[30:21], 1'b0};
					we_reg = 1;
					we = 4'b0;
					regdata = PC + 4;
					nextPC = (PC+imm);
                end
        endcase
    end  

    R_Type alu1(func3, func7, rv1, rv2, R_type_result);
    I_Type immI(instr32[30], imm, rv1, func3, I_type_result);
    I2_Type loadOp(func3, daddr, drdata, I2_type_result);
    S_Type memStore(func3, daddr, we_S_result);
    B_type BrandL(rv1, rv2, func3, B_type_result);
endmodule

CtrlUnit_tb.v
`include "CtrlUnit.v"
`timescale 1ns / 1ps

module CTRL_UNIT_TB();
    reg clk, reset;
    wire [31:0] PC;
    wire [31:0] nextPC;
    wire isDone;

    CTRL_UNIT riscv(clk, reset, PC, nextPC, isDone);
	 
    initial begin
        clk=0;
        repeat(50000) #5 clk = ~clk;
    end 

    initial begin
        $dumpfile("CtrlUnit_tb.vcd");
        $dumpvars(0, CTRL_UNIT_TB);

        clk = 0;
        reset = 1;
        #10;
        reset = 0;
    end

    always @(isDone) begin
        if (isDone == 1'b1) begin
            $display("The execution has finished.");
            $finish;
        end
    end
endmodule

CtrlUnit_tb.vcd
$date
	Sat Nov  4 14:23:48 2023
$end
$version
	Icarus Verilog
$end
$timescale
	1ps
$end
$scope module CTRL_UNIT_TB $end
$var wire 32 ! nextPC [31:0] $end
$var wire 1 " isDone $end
$var wire 32 # PC [31:0] $end
$var reg 1 $ clk $end
$var reg 1 % reset $end
$scope module riscv $end
$var wire 1 $ clk $end
$var wire 1 % reset $end
$var wire 4 & we_S_result [3:0] $end
$var wire 32 ' rv2 [31:0] $end
$var wire 32 ( rv1 [31:0] $end
$var wire 32 ) instr32 [31:0] $end
$var wire 32 * drdata [31:0] $end
$var wire 32 + R_type_result [31:0] $end
$var wire 32 , I_type_result [31:0] $end
$var wire 32 - I2_type_result [31:0] $end
$var wire 1 . B_type_result $end
$var reg 32 / PC [31:0] $end
$var reg 32 0 daddr [31:0] $end
$var reg 32 1 dwdata [31:0] $end
$var reg 3 2 func3 [2:0] $end
$var reg 7 3 func7 [6:0] $end
$var reg 32 4 imm [31:0] $end
$var reg 1 " isDone $end
$var reg 32 5 nextPC [31:0] $end
$var reg 5 6 rd [4:0] $end
$var reg 32 7 regdata [31:0] $end
$var reg 5 8 rs1 [4:0] $end
$var reg 5 9 rs2 [4:0] $end
$var reg 4 : we [3:0] $end
$var reg 1 ; we_reg $end
$scope module BrandL $end
$var wire 3 < func3 [2:0] $end
$var wire 32 = tempA [31:0] $end
$var wire 32 > tempB [31:0] $end
$var wire 32 ? rv2 [31:0] $end
$var wire 32 @ rv1 [31:0] $end
$var reg 1 . result $end
$upscope $end
$scope module alu1 $end
$var wire 3 A func3 [2:0] $end
$var wire 7 B func7 [6:0] $end
$var wire 32 C tempA [31:0] $end
$var wire 32 D tempB [31:0] $end
$var wire 32 E operator2 [31:0] $end
$var wire 32 F operator1 [31:0] $end
$var reg 32 G out [31:0] $end
$upscope $end
$scope module dm1 $end
$var wire 32 H address [31:0] $end
$var wire 1 $ clk $end
$var wire 32 I dwdata [31:0] $end
$var wire 4 J we [3:0] $end
$var wire 32 K drdata [31:0] $end
$var wire 32 L byte3 [31:0] $end
$var wire 32 M byte2 [31:0] $end
$var wire 32 N byte1 [31:0] $end
$var wire 32 O byte0 [31:0] $end
$upscope $end
$scope module im1 $end
$var wire 32 P iaddr [31:0] $end
$var wire 32 Q idata [31:0] $end
$upscope $end
$scope module immI $end
$var wire 3 R func3 [2:0] $end
$var wire 32 S imm [31:0] $end
$var wire 1 T srli_e $end
$var wire 32 U tempA [31:0] $end
$var wire 12 V tempB [11:0] $end
$var wire 32 W rdata1 [31:0] $end
$var reg 32 X out [31:0] $end
$upscope $end
$scope module loadOp $end
$var wire 32 Y address [31:0] $end
$var wire 32 Z drdata [31:0] $end
$var wire 3 [ func3 [2:0] $end
$var reg 32 \ offset [31:0] $end
$var reg 32 ] out [31:0] $end
$upscope $end
$scope module memStore $end
$var wire 32 ^ address [31:0] $end
$var wire 3 _ func3 [2:0] $end
$var reg 4 ` we_out [3:0] $end
$upscope $end
$scope module reg1 $end
$var wire 1 $ clk $end
$var wire 5 a rd [4:0] $end
$var wire 32 b regdata [31:0] $end
$var wire 5 c rs1 [4:0] $end
$var wire 5 d rs2 [4:0] $end
$var wire 32 e rv1 [31:0] $end
$var wire 32 f rv2 [31:0] $end
$var wire 1 ; wer $end
$var integer 32 g i [31:0] $end
$upscope $end
$upscope $end
$upscope $end
$enddefinitions $end
#0
$dumpvars
b100000 g
bx f
bx e
bx d
bx c
bx b
bx a
bx `
bx _
bx ^
bx ]
bx \
bx [
bx Z
bx Y
bx X
bx W
bx V
bx U
xT
bx S
bx R
bx Q
bx P
bx O
bx N
bx M
bx L
bx K
bx J
bx I
bx H
bx G
bx F
bx E
bx D
bx C
bx B
bx A
bx @
bx ?
bx >
bx =
bx <
x;
bx :
bx 9
bx 8
bx 7
bx 6
bx 5
bx 4
bx 3
bx 2
bx 1
bx 0
bx /
x.
bx -
bx ,
bx +
bx *
bx )
bx (
bx '
bx &
1%
0$
bx #
x"
bx !
$end
#5000
b1000100 V
0T
b1000100 !
b1000100 5
b100 7
b100 b
b0 :
b0 J
1;
b1000100 4
b1000100 S
b0 6
b0 a
b100010000000000000001101111 )
b100010000000000000001101111 Q
b0 #
b0 /
b0 P
1$
#10000
0$
0%
#15000
b0xx000 \
b11 ,
b11 X
b11 V
b1010 6
b1010 a
b0 2
b0 <
b0 A
b0 R
b0 [
b0 _
b0 U
b0 C
b0 =
b0 (
b0 @
b0 F
b0 W
b0 e
b0 8
b0 c
b11 4
b11 S
b1100000000010100010011 )
b1100000000010100010011 Q
b1001000 !
b1001000 5
b11 7
b11 b
b1000100 #
b1000100 /
b1000100 P
1$
#20000
0$
#25000
b11111111111111111111111110111100 ,
b11111111111111111111111110111100 X
b111110111100 V
1T
b1001100 7
b1001100 b
b11111111111111111111111110111100 4
b11111111111111111111111110111100 S
b1 6
b1 a
b11111011110111111111000011101111 )
b11111011110111111111000011101111 Q
b100 !
b100 5
b1001000 #
b1001000 /
b1001000 P
1$
#30000
0$
#35000
b10000 ,
b10000 X
b10000 V
0T
b10 6
b10 a
b10 8
b10 c
b10000 4
b10000 S
b1000000010000000100010011 )
b1000000010000000100010011 Q
b1000 !
b1000 5
b10000 7
b10000 b
b100 #
b100 /
b100 P
1$
#40000
0$
#45000
b0 -
b0 ]
b11000 O
b11001 N
b11010 M
b0 *
b0 K
b0 Z
b11011 L
b0 \
b1111 &
b1111 `
b1 +
b1 G
b1000 V
b1111 :
b1111 J
b1001100 1
b1001100 I
b11000 0
b11000 H
b11000 Y
b11000 ^
b10 2
b10 <
b10 A
b10 R
b10 [
b10 _
b1001100 D
b1001100 >
b1001100 '
b1001100 ?
b1001100 E
b1001100 f
b1 9
b1 d
b1000 4
b1000 S
b0 ,
b0 X
b100010010010000100011 )
b100010010010000100011 Q
b1100 !
b1100 5
b10000 U
b10000 C
b10000 =
b10000 (
b10000 @
b10000 F
b10000 W
b10000 e
b1000 #
b1000 /
b1000 P
1$
#50000
0$
#55000
b10000 O
b10001 N
b10010 M
b10011 L
b0 +
b0 G
b0 V
b11 1
b11 I
b10000 0
b10000 H
b10000 Y
b10000 ^
b11 D
b11 >
b11 '
b11 ?
b11 E
b11 f
b1010 9
b1010 d
b0 4
b0 S
b101000010010000000100011 )
b101000010010000000100011 Q
b10000 !
b10000 5
b0 -
b0 ]
b1100 #
b1100 /
b1100 P
b0 *
b0 K
b0 Z
1$
#60000
0$
#65000
b1 &
b1 `
1.
b10 ,
b10 X
b111111111111 V
1T
b10 7
b10 b
b0 :
b0 J
b101 6
b101 a
b0 2
b0 <
b0 A
b0 R
b0 [
b0 _
b11 U
b11 C
b11 =
b11 (
b11 @
b11 F
b11 W
b11 e
b1010 8
b1010 c
b11111111111111111111111111111111 4
b11111111111111111111111111111111 S
b11 -
b11 ]
b11111111111101010000001010010011 )
b11111111111101010000001010010011 Q
b10100 !
b10100 5
b11 *
b11 K
b11 Z
b10000 #
b10000 /
b10000 P
1$
#70000
0$
#75000
b10000 V
b10 +
b10 G
b0 ,
b0 X
0T
0;
b10000 4
b10000 S
b101 2
b101 <
b101 A
b101 R
b101 [
b101 _
b0 D
b0 >
b0 '
b0 ?
b0 E
b0 f
b0 9
b0 d
b10 U
b10 C
b10 =
b10 (
b10 @
b10 F
b10 W
b10 e
b101 8
b101 c
b101101100001100011 )
b101101100001100011 Q
b100100 !
b100100 5
b10100 #
b10100 /
b10100 P
1$
#80000
0$
#85000
0.
b10 ,
b10 X
b111111111111 V
1T
b10 7
b10 b
1;
b1010 6
b1010 a
b0 2
b0 <
b0 A
b0 R
b0 [
b0 _
b11 U
b11 C
b11 =
b11 (
b11 @
b11 F
b11 W
b11 e
b1010 8
b1010 c
b11111111111111111111111111111111 4
b11111111111111111111111111111111 S
b11111111111101010000010100010011 )
b11111111111101010000010100010011 Q
b101000 !
b101000 5
b100100 #
b100100 /
b100100 P
1$
#90000
0$
#95000
b111111011100 V
b11111111111111111111111111011100 4
b11111111111111111111111111011100 S
b1 6
b1 a
b11111101110111111111000011101111 )
b11111101110111111111000011101111 Q
b100 !
b100 5
b101100 7
b101100 b
b11111111111111111111111111011110 ,
b11111111111111111111111111011110 X
b101000 #
b101000 /
b101000 P
b10 U
b10 C
b10 =
b10 (
b10 @
b10 F
b10 W
b10 e
1$
#100000
0$
#105000
b100000 ,
b100000 X
b10000 V
0T
b10 6
b10 a
b10000 U
b10000 C
b10000 =
b10000 (
b10000 @
b10000 F
b10000 W
b10000 e
b10 8
b10 c
b10000 4
b10000 S
b1000000010000000100010011 )
b1000000010000000100010011 Q
b1000 !
b1000 5
b100000 7
b100000 b
b100 #
b100 /
b100 P
1$
#110000
0$
#115000
b0 -
b0 ]
b0 *
b0 K
b0 Z
b101000 O
b101001 N
b101010 M
b101011 L
b1111 &
b1111 `
b1 +
b1 G
b1000 V
b1111 :
b1111 J
b101100 1
b101100 I
b101000 0
b101000 H
b101000 Y
b101000 ^
b10 2
b10 <
b10 A
b10 R
b10 [
b10 _
b101100 D
b101100 >
b101100 '
b101100 ?
b101100 E
b101100 f
b1 9
b1 d
b1000 4
b1000 S
b100010010010000100011 )
b100010010010000100011 Q
b1100 !
b1100 5
b110000 7
b110000 b
b0 ,
b0 X
b1000 #
b1000 /
b1000 P
b100000 U
b100000 C
b100000 =
b100000 (
b100000 @
b100000 F
b100000 W
b100000 e
1$
#120000
0$
#125000
b0 V
b10 1
b10 I
b10 D
b10 >
b10 '
b10 ?
b10 E
b10 f
b1010 9
b1010 d
b0 4
b0 S
b110000 O
b110001 N
b110010 M
b110011 L
b0 -
b0 ]
b0 +
b0 G
b101000010010000000100011 )
b101000010010000000100011 Q
b10000 !
b10000 5
b110000 0
b110000 H
b110000 Y
b110000 ^
b0 *
b0 K
b0 Z
b110000 U
b110000 C
b110000 =
b110000 (
b110000 @
b110000 F
b110000 W
b110000 e
b1100 #
b1100 /
b1100 P
1$
#130000
0$
#135000
b1 &
b1 `
1.
b1 ,
b1 X
b111111111111 V
1T
b1 7
b1 b
b0 :
b0 J
b101 6
b101 a
b0 2
b0 <
b0 A
b0 R
b0 [
b0 _
b10 U
b10 C
b10 =
b10 (
b10 @
b10 F
b10 W
b10 e
b1010 8
b1010 c
b11111111111111111111111111111111 4
b11111111111111111111111111111111 S
b11111111111101010000001010010011 )
b11111111111101010000001010010011 Q
b10100 !
b10100 5
b10 -
b10 ]
b10000 #
b10000 /
b10000 P
b10 *
b10 K
b10 Z
1$
#140000
0$
#145000
b10000 V
b1 +
b1 G
b0 ,
b0 X
0T
0;
b10000 4
b10000 S
b101 2
b101 <
b101 A
b101 R
b101 [
b101 _
b0 D
b0 >
b0 '
b0 ?
b0 E
b0 f
b0 9
b0 d
b1 U
b1 C
b1 =
b1 (
b1 @
b1 F
b1 W
b1 e
b101 8
b101 c
b101101100001100011 )
b101101100001100011 Q
b100100 !
b100100 5
b10100 #
b10100 /
b10100 P
1$
#150000
0$
#155000
0.
b1 ,
b1 X
b111111111111 V
1T
b1 7
b1 b
1;
b1010 6
b1010 a
b0 2
b0 <
b0 A
b0 R
b0 [
b0 _
b10 U
b10 C
b10 =
b10 (
b10 @
b10 F
b10 W
b10 e
b1010 8
b1010 c
b11111111111111111111111111111111 4
b11111111111111111111111111111111 S
b11111111111101010000010100010011 )
b11111111111101010000010100010011 Q
b101000 !
b101000 5
b100100 #
b100100 /
b100100 P
1$
#160000
0$
#165000
b111111011100 V
b101100 7
b101100 b
b11111111111111111111111111011100 4
b11111111111111111111111111011100 S
b1 6
b1 a
b11111111111111111111111111011101 ,
b11111111111111111111111111011101 X
b11111101110111111111000011101111 )
b11111101110111111111000011101111 Q
b100 !
b100 5
b1 U
b1 C
b1 =
b1 (
b1 @
b1 F
b1 W
b1 e
b101000 #
b101000 /
b101000 P
1$
#170000
0$
#175000
b1000000 ,
b1000000 X
b10000 V
0T
b10 6
b10 a
b110000 U
b110000 C
b110000 =
b110000 (
b110000 @
b110000 F
b110000 W
b110000 e
b10 8
b10 c
b10000 4
b10000 S
b1000000010000000100010011 )
b1000000010000000100010011 Q
b1000 !
b1000 5
b1000000 7
b1000000 b
b100 #
b100 /
b100 P
1$
#180000
0$
#185000
b0 -
b0 ]
b0 *
b0 K
b0 Z
b1001000 O
b1001001 N
b1001010 M
b1001011 L
b1111 &
b1111 `
b0 +
b0 G
b1000 V
b1111 :
b1111 J
b101100 1
b101100 I
b1001000 0
b1001000 H
b1001000 Y
b1001000 ^
b10 2
b10 <
b10 A
b10 R
b10 [
b10 _
b101100 D
b101100 >
b101100 '
b101100 ?
b101100 E
b101100 f
b1 9
b1 d
b1000 4
b1000 S
b0 ,
b0 X
b100010010010000100011 )
b100010010010000100011 Q
b1100 !
b1100 5
b1000000 U
b1000000 C
b1000000 =
b1000000 (
b1000000 @
b1000000 F
b1000000 W
b1000000 e
b1000 #
b1000 /
b1000 P
1$
#190000
0$
#195000
b1000000 O
b1000001 N
b1000010 M
b1000011 L
b0 V
b1 1
b1 I
b1000000 0
b1000000 H
b1000000 Y
b1000000 ^
b1 D
b1 >
b1 '
b1 ?
b1 E
b1 f
b1010 9
b1010 d
b0 4
b0 S
b101000010010000000100011 )
b101000010010000000100011 Q
b10000 !
b10000 5
b0 -
b0 ]
b1100 #
b1100 /
b1100 P
b0 *
b0 K
b0 Z
1$
#200000
0$
#205000
b1 &
b1 `
1.
b111111111111 V
1T
b0 7
b0 b
b0 :
b0 J
b101 6
b101 a
b0 2
b0 <
b0 A
b0 R
b0 [
b0 _
b1 U
b1 C
b1 =
b1 (
b1 @
b1 F
b1 W
b1 e
b1010 8
b1010 c
b11111111111111111111111111111111 4
b11111111111111111111111111111111 S
b1 -
b1 ]
b11111111111101010000001010010011 )
b11111111111101010000001010010011 Q
b10100 !
b10100 5
b1 *
b1 K
b1 Z
b10000 #
b10000 /
b10000 P
1$
#210000
0$
#215000
b10000 V
0T
0;
b10000 4
b10000 S
b101 2
b101 <
b101 A
b101 R
b101 [
b101 _
b0 D
b0 >
b0 '
b0 ?
b0 E
b0 f
b0 9
b0 d
b0 U
b0 C
b0 =
b0 (
b0 @
b0 F
b0 W
b0 e
b101 8
b101 c
b101101100001100011 )
b101101100001100011 Q
b100100 !
b100100 5
b10100 #
b10100 /
b10100 P
1$
#220000
0$
#225000
0.
b111111111111 V
1T
1;
b1010 6
b1010 a
b0 2
b0 <
b0 A
b0 R
b0 [
b0 _
b1 U
b1 C
b1 =
b1 (
b1 @
b1 F
b1 W
b1 e
b1010 8
b1010 c
b11111111111111111111111111111111 4
b11111111111111111111111111111111 S
b11111111111101010000010100010011 )
b11111111111101010000010100010011 Q
b101000 !
b101000 5
b100100 #
b100100 /
b100100 P
1$
#230000
0$
#235000
b111111011100 V
b11111111111111111111111111011100 4
b11111111111111111111111111011100 S
b1 6
b1 a
b11111101110111111111000011101111 )
b11111101110111111111000011101111 Q
b100 !
b100 5
b101100 7
b101100 b
1.
b11111111111111111111111111011100 ,
b11111111111111111111111111011100 X
b101000 #
b101000 /
b101000 P
b0 U
b0 C
b0 =
b0 (
b0 @
b0 F
b0 W
b0 e
1$
#240000
0$
#245000
0.
b1010000 ,
b1010000 X
b10000 V
0T
b10 6
b10 a
b1000000 U
b1000000 C
b1000000 =
b1000000 (
b1000000 @
b1000000 F
b1000000 W
b1000000 e
b10 8
b10 c
b10000 4
b10000 S
b1000000010000000100010011 )
b1000000010000000100010011 Q
b1000 !
b1000 5
b1010000 7
b1010000 b
b100 #
b100 /
b100 P
1$
#250000
0$
#255000
b0 -
b0 ]
b0 *
b0 K
b0 Z
b1011000 O
b1011001 N
b1011010 M
b1011011 L
b1111 &
b1111 `
b1000 V
b1111 :
b1111 J
b101100 1
b101100 I
b1011000 0
b1011000 H
b1011000 Y
b1011000 ^
b10 2
b10 <
b10 A
b10 R
b10 [
b10 _
b101100 D
b101100 >
b101100 '
b101100 ?
b101100 E
b101100 f
b1 9
b1 d
b1000 4
b1000 S
b100010010010000100011 )
b100010010010000100011 Q
b1100 !
b1100 5
b1100000 7
b1100000 b
b0 ,
b0 X
b1000 #
b1000 /
b1000 P
b1010000 U
b1010000 C
b1010000 =
b1010000 (
b1010000 @
b1010000 F
b1010000 W
b1010000 e
1$
#260000
0$
#265000
b0 V
b0 1
b0 I
b0 D
b0 >
b0 '
b0 ?
b0 E
b0 f
b1010 9
b1010 d
b0 4
b0 S
b1100000 O
b1100001 N
b1100010 M
b1100011 L
b0 -
b0 ]
b101000010010000000100011 )
b101000010010000000100011 Q
b10000 !
b10000 5
b1100000 0
b1100000 H
b1100000 Y
b1100000 ^
b0 *
b0 K
b0 Z
b1100000 U
b1100000 C
b1100000 =
b1100000 (
b1100000 @
b1100000 F
b1100000 W
b1100000 e
b1100 #
b1100 /
b1100 P
1$
#270000
0$
#275000
b1 &
b1 `
1.
b11111111111111111111111111111111 ,
b11111111111111111111111111111111 X
b111111111111 V
1T
b11111111111111111111111111111111 7
b11111111111111111111111111111111 b
b0 :
b0 J
b101 6
b101 a
b0 2
b0 <
b0 A
b0 R
b0 [
b0 _
b0 U
b0 C
b0 =
b0 (
b0 @
b0 F
b0 W
b0 e
b1010 8
b1010 c
b11111111111111111111111111111111 4
b11111111111111111111111111111111 S
b11111111111101010000001010010011 )
b11111111111101010000001010010011 Q
b10100 !
b10100 5
b10000 #
b10000 /
b10000 P
1$
#280000
0$
#285000
b10000 V
0.
b11111111111111111111111111111111 +
b11111111111111111111111111111111 G
0T
0;
b10000 4
b10000 S
b101 2
b101 <
b101 A
b101 R
b101 [
b101 _
b0 9
b0 d
b11111111111111111111111111111111 U
b11111111111111111111111111111111 C
b11111111111111111111111111111111 =
b11111111111111111111111111111111 (
b11111111111111111111111111111111 @
b11111111111111111111111111111111 F
b11111111111111111111111111111111 W
b11111111111111111111111111111111 e
b101 8
b101 c
b101101100001100011 )
b101101100001100011 Q
b11000 !
b11000 5
b10100 #
b10100 /
b10100 P
1$
#290000
0$
#295000
b1 7
b1 b
1.
b1 ,
b1 X
b1 V
1;
b1010 6
b1010 a
b0 2
b0 <
b0 A
b0 R
b0 [
b0 _
b0 U
b0 C
b0 =
b0 (
b0 @
b0 F
b0 W
b0 e
b0 8
b0 c
b1 4
b1 S
b100000000010100010011 )
b100000000010100010011 Q
b11100 !
b11100 5
b11000 #
b11000 /
b11000 P
1$
#300000
0$
#305000
b1010000 7
b1010000 b
0.
b1010000 ,
b1010000 X
b111111110000 V
1T
b10 6
b10 a
b1100000 U
b1100000 C
b1100000 =
b1100000 (
b1100000 @
b1100000 F
b1100000 W
b1100000 e
b10 8
b10 c
b11111111111111111111111111110000 4
b11111111111111111111111111110000 S
b11111111000000010000000100010011 )
b11111111000000010000000100010011 Q
b100000 !
b100000 5
b11100 #
b11100 /
b11100 P
1$
#310000
0$
